MANIFEST.in
README.md
requirements.txt
setup.py
version.py
bin/ripio
ripio/__init__.py
ripio/cli.py
ripio/utils.py
ripio.egg-info/PKG-INFO
ripio.egg-info/SOURCES.txt
ripio.egg-info/dependency_links.txt
ripio.egg-info/requires.txt
ripio.egg-info/top_level.txt