Metadata-Version: 2.4
Name: ripio
Version: 0.20251227
Summary: git repositories from command line
Home-page: https://github.com/davidvilla/ripio
Author: David Villa Alises
Author-email: David.Villa@gmail.com
License: GPL v2 or later
Classifier: Programming Language :: Python :: 3
Requires-Dist: requests
Requires-Dist: gitpython
Requires-Dist: toml
Dynamic: author
Dynamic: author-email
Dynamic: classifier
Dynamic: description
Dynamic: description-content-type
Dynamic: home-page
Dynamic: license
Dynamic: requires-dist
Dynamic: summary
